allotools/__init__.py
allotools/allo_use_plot.py
allotools/allocation_ts.py
allotools/core.py
allotools/data_io.py
allotools/plot.py
allotools/utils.py
nz_allo_usage_tools-0.2.10.dist-info/METADATA
nz_allo_usage_tools-0.2.10.dist-info/WHEEL
nz_allo_usage_tools-0.2.10.dist-info/licenses/LICENSE
nz_allo_usage_tools-0.2.10.dist-info/RECORD
